video_subtitles/__init__.py
video_subtitles/cli.py
video_subtitles/convert_to_webvtt.py
video_subtitles/gui.py
video_subtitles/run.py
video_subtitles/say.py
video_subtitles/settings.py
video_subtitles/thread_processor.py
video_subtitles/translate.py
video_subtitles/util.py
video_subtitles/assets/example.txt
video_subtitles-1.0.11.dist-info/LICENSE
video_subtitles-1.0.11.dist-info/METADATA
video_subtitles-1.0.11.dist-info/WHEEL
video_subtitles-1.0.11.dist-info/entry_points.txt
video_subtitles-1.0.11.dist-info/top_level.txt
video_subtitles-1.0.11.dist-info/RECORD
