Metadata-Version: 2.1
Name: video-subtitles
Version: 1.0.11
Summary: Creates Video Subtitles
Home-page: https://github.com/zackees/video-subtitles
Maintainer: Zachary Vorhies
License: BSD 3-Clause License
Keywords: template-python-cmd
Classifier: Programming Language :: Python :: 3
Requires-Python: >=3.7
License-File: LICENSE
Requires-Dist: download (==0.3.5)
Requires-Dist: srtranslator (==0.2.6)
Requires-Dist: gTTS (==2.3.2)
Requires-Dist: playaudio (==1.0.5)
Requires-Dist: PyQt6 (==6.3.1)
Requires-Dist: webvtt-py (==0.4.6)
Requires-Dist: appdirs (==1.4.4)
Requires-Dist: disklru (>=1.0.5)
